[
    {
        "id": 1,
        "short_description": "RadioButtons",
        "long_description": "Radio buttons (no textbox)",
        "requires_sub_uid": "N",
        "comments": "May be interpreted differently on some blocks"
    },
    {
        "id": 2,
        "short_description": "RadioButtons_TextboxLastEntry",
        "long_description": "Radio buttons with a textbox for the last entry",
        "requires_sub_uid": "Y",
        "comments": null
    },
    {
        "id": 3,
        "short_description": "Checkboxes",
        "long_description": "Checkboxes (no textbox)",
        "requires_sub_uid": "N",
        "comments": null
    },
    {
        "id": 4,
        "short_description": "Checkboxes_TextboxLastEntry",
        "long_description": "Checkboxes with a textbox associated to the last entry (last checkbox).  Usually, the textbox is only shown if the last checkbox is selected.",
        "requires_sub_uid": "Y",
        "comments": "Usually used for \"Other\"."
    },
    {
        "id": 5,
        "short_description": "Checkboxes_ConditionalTextbox2",
        "long_description": "Checkboxes with a conditional question with textbox in the 2nd answer option",
        "requires_sub_uid": "Y",
        "comments": "So far, only used for water source question"
    },
    {
        "id": 6,
        "short_description": "Textbox",
        "long_description": "Textbox",
        "requires_sub_uid": "N",
        "comments": "Textbox"
    },
    {
        "id": 7,
        "short_description": "DropDown",
        "long_description": "Drop-down list box for mutually exclusive answers",
        "requires_sub_uid": "N",
        "comments": "Drop-down box"
    },
    {
        "id": 8,
        "short_description": "No_Answer",
        "long_description": "SRE.UID does not require any direct answer.",
        "requires_sub_uid": "N",
        "comments": null
    },
    {
        "id": 9,
        "short_description": "Date_MonthDayYear",
        "long_description": "Date (month, day, and year)",
        "requires_sub_uid": "N",
        "comments": "Entered using the Calendar widget"
    },
    {
        "id": 10,
        "short_description": "MatrixRadioButtons",
        "long_description": "Matrix of radio buttons only",
        "requires_sub_uid": "Y",
        "comments": null
    },
    {
        "id": 11,
        "short_description": "MatrixRadioButtons_DropDownLastCol",
        "long_description": "Matrix of radio buttons with a drop-down box in the last column",
        "requires_sub_uid": "Y",
        "comments": null
    },
    {
        "id": 12,
        "short_description": "MatrixRadioButtons_TextboxLastRow",
        "long_description": "Matrix of radio buttons with the last row having a textbox",
        "requires_sub_uid": "Y",
        "comments": null
    },
    {
        "id": 13,
        "short_description": "RadioButtons_in_Matrix_DropDownLastCol",
        "long_description": "Radio buttons in a matrix where the last column is a drop-down box",
        "requires_sub_uid": "Y",
        "comments": null
    },
    {
        "id": 14,
        "short_description": "Textbox_in_Matrix",
        "long_description": "Textbox within a matrix",
        "requires_sub_uid": "N",
        "comments": "For now, only possible when the parent of this element has ANCA.ID=12"
    },
    {
        "id": 15,
        "short_description": "RadioButons_in_Matrix",
        "long_description": "Radio buttons within a matrix",
        "requires_sub_uid": "N",
        "comments": null
    },
    {
        "id": 16,
        "short_description": "Calculated",
        "long_description": "Value calculated or copied from subsequent questions/elements",
        "requires_sub_uid": "N",
        "comments": "Example:  The expected answer for the height is the height in inches (float) calculated from the values written in the Ft and In textboxes"
    },
    {
        "id": 17,
        "short_description": "Address",
        "long_description": "Address structure",
        "requires_sub_uid": "N",
        "comments": null
    },
    {
        "id": 18,
        "short_description": "Immediate_Selection",
        "long_description": "Similar to radio buttons, but used to select mutually exclusive answers and immediately go to the next page without having to click on any next button.",
        "requires_sub_uid": "N",
        "comments": "E.g.:  This answer category applies to the three buttons the respondent use to select their type (parent of minor proband, legally authorized representative of adult proband,or self-reporting adult proband).  It also applies to the Add Address buttons."
    }
]